{
  "model": {
    "type": "minecraft:range_dispatch",
    "property": "minecraft:custom_model_data",
    "fallback": {
      "type": "minecraft:model",
      "model": "minecraft:item/cauldron"
    },
    "entries": [
      {
        "threshold": 610001,
        "model": {
          "type": "minecraft:model",
          "model": "maeflowers:bathroom/cauldron_bath_faucet"
        }
      },
      {
        "threshold": 610002,
        "model": {
          "type": "minecraft:model",
          "model": "maeflowers:bathroom/cauldron_bathtub"
        }
      }
    ]
  }
}
