{
    "parent": "item/generated",
    "textures": {
        "layer0": "item/extended_equipment/crossbow/pistol_standby"
    },
    "display": {
        "thirdperson_righthand": {
			"rotation": [-45, -90, 0],
            "translation": [ 0, 0.75, -3 ],
            "scale": [ 0.9, 0.9, 0.9 ]
        },
        "thirdperson_lefthand": {
			"rotation": [-45, 90, 0],
            "translation": [ 0, 0.75, -3 ],
            "scale": [ 0.9, 0.9, 0.9 ]
        },
        "firstperson_righthand": {
			"rotation": [-35, -90, 0],
            "translation": [ 1.13, 3.2, 1.13],
            "scale": [ 0.68, 0.68, 0.68 ]
        },
        "firstperson_lefthand": {
			"rotation": [-180, 85, 145],
            "translation": [ 1.13, 3.2, 1.13],
            "scale": [ 0.68, 0.68, 0.68 ]
        }
    },
    "overrides": [
        {
            "predicate": {
                "reloading": 1
            },
            "model": "item/pistol_reloading_0"
        },
        {
            "predicate": {
                "reloading": 1,
                "pull": 0.58
            },
            "model": "item/pistol_reloading_1"
        },
        {
            "predicate": {
                "reloading": 1,
                "pull": 1.0
            },
            "model": "item/pistol_reloading_2"
        },
        {
            "predicate": {
                "charged": 1
            },
            "model": "item/pistol_arrow"
        },
        {
            "predicate": {
                "charged": 1,
                "firework": 1
            },
            "model": "item/pistol_firework"
        }
    ]
}
